crowdcores/__init__.py
crowdcores/pipeline.py
pipeline/__init__.py
pipeline/pipeline.py
crowdcores-1.0.5.dist-info/LICENSE.txt
crowdcores-1.0.5.dist-info/METADATA
crowdcores-1.0.5.dist-info/WHEEL
crowdcores-1.0.5.dist-info/top_level.txt
crowdcores-1.0.5.dist-info/RECORD
